{
  "departments_courses": {
    "Computer Science": [
      "Introduction to Programming",
      "Data Structures and Algorithms",
      "Database Management Systems",
      "Web Development",
      "Artificial Intelligence",
      "Machine Learning",
      "Computer Networks",
      "Operating Systems",
      "Software Engineering",
      "Cybersecurity Fundamentals",
      "Software Testing and Quality Assurance",
      "Human-Computer Interaction",
      "Mobile App Development",
      "Cloud Computing",
      "Big Data Analytics",
      "Internet of Things (IoT)",
      "Embedded Systems",
      "Computational Geometry",
      "Programming Languages and Compilers",
      "Advanced Algorithms",
      "Computer Science Foundations",
      "Computer Science Advanced Topics",
      "Computer Science Applications",
      "Computer Science Techniques",
      "Computer Science Seminar",
      "Computer Science Workshop",
      "Computer Science Research Methods",
      "Computer Science Case Studies",
      "Computer Science Systems",
      "Computer Science Principles",
      "Computer Science Innovation",
      "Computer Science Design",
      "Computer Science Development",
      "Computer Science Modeling",
      "Computer Science Integration",
      "Computer Science Simulation",
      "Computer Science Implementation",
      "Computer Science Management",
      "Computer Science Trends",
      "Computer Science Analytics",
      "Computer Science Optimization",
      "Computer Science Dynamics",
      "Computer Science Ethics",
      "Computer Science Practices",
      "Computer Science Technology",
      "Computer Science Engineering",
      "Computer Science Performance",
      "Computer Science Computing",
      "Computer Science Evaluation",
      "Computer Science Methodologies"
    ],
    "Mathematics": [
      "Calculus I",
      "Calculus II",
      "Linear Algebra",
      "Probability and Statistics",
      "Differential Equations",
      "Discrete Mathematics",
      "Number Theory",
      "Abstract Algebra",
      "Real Analysis",
      "Mathematical Modeling",
      "Topology",
      "Complex Analysis",
      "Mathematical Logic",
      "Combinatorics",
      "Graph Theory",
      "Optimization Theory",
      "Stochastic Processes",
      "Functional Analysis",
      "Mathematical Finance",
      "Cryptography",
      "Mathematics Foundations",
      "Mathematics Advanced Topics",
      "Mathematics Applications",
      "Mathematics Techniques",
      "Mathematics Seminar",
      "Mathematics Workshop",
      "Mathematics Research Methods",
      "Mathematics Case Studies",
      "Mathematics Systems",
      "Mathematics Principles",
      "Mathematics Innovation",
      "Mathematics Design",
      "Mathematics Development",
      "Mathematics Modeling",
      "Mathematics Integration",
      "Mathematics Simulation",
      "Mathematics Implementation",
      "Mathematics Management",
      "Mathematics Trends",
      "Mathematics Analytics",
      "Mathematics Optimization",
      "Mathematics Dynamics",
      "Mathematics Ethics",
      "Mathematics Practices",
      "Mathematics Technology",
      "Mathematics Engineering",
      "Mathematics Performance",
      "Mathematics Computing",
      "Mathematics Evaluation",
      "Mathematics Methodologies"
    ],
    "Physics": [
      "Classical Mechanics",
      "Electromagnetism",
      "Quantum Physics",
      "Thermodynamics",
      "Optics and Waves",
      "Statistical Mechanics",
      "Nuclear Physics",
      "Solid State Physics",
      "Astrophysics",
      "Particle Physics",
      "Plasma Physics",
      "Computational Physics",
      "Biophysics",
      "Geophysics",
      "Condensed Matter Physics",
      "Optoelectronics",
      "Atomic and Molecular Physics",
      "Mathematical Methods in Physics",
      "Relativity",
      "Instrumentation and Measurement",
      "Physics Foundations",
      "Physics Advanced Topics",
      "Physics Applications",
      "Physics Techniques",
      "Physics Seminar",
      "Physics Workshop",
      "Physics Research Methods",
      "Physics Case Studies",
      "Physics Systems",
      "Physics Principles",
      "Physics Innovation",
      "Physics Design",
      "Physics Development",
      "Physics Modeling",
      "Physics Integration",
      "Physics Simulation",
      "Physics Implementation",
      "Physics Management",
      "Physics Trends",
      "Physics Analytics",
      "Physics Optimization",
      "Physics Dynamics",
      "Physics Ethics",
      "Physics Practices",
      "Physics Technology",
      "Physics Engineering",
      "Physics Performance",
      "Physics Computing",
      "Physics Evaluation",
      "Physics Methodologies"
    ],
    "Business Administration": [
      "Principles of Management",
      "Financial Accounting",
      "Marketing Fundamentals",
      "Business Strategy",
      "Organizational Behavior",
      "Operations Management",
      "Business Ethics",
      "Entrepreneurship",
      "International Business",
      "Human Resource Management",
      "Supply Chain Management",
      "Strategic Management",
      "Business Analytics",
      "Corporate Finance",
      "Consumer Behavior",
      "Leadership and Negotiation",
      "Risk Management",
      "E-Commerce",
      "Project Management",
      "Organizational Change",
      "Business Administration Foundations",
      "Business Administration Advanced Topics",
      "Business Administration Applications",
      "Business Administration Techniques",
      "Business Administration Seminar",
      "Business Administration Workshop",
      "Business Administration Research Methods",
      "Business Administration Case Studies",
      "Business Administration Systems",
      "Business Administration Principles",
      "Business Administration Innovation",
      "Business Administration Design",
      "Business Administration Development",
      "Business Administration Modeling",
      "Business Administration Integration",
      "Business Administration Simulation",
      "Business Administration Implementation",
      "Business Administration Management",
      "Business Administration Trends",
      "Business Administration Analytics",
      "Business Administration Optimization",
      "Business Administration Dynamics",
      "Business Administration Ethics",
      "Business Administration Practices",
      "Business Administration Technology",
      "Business Administration Engineering",
      "Business Administration Performance",
      "Business Administration Computing",
      "Business Administration Evaluation",
      "Business Administration Methodologies"
    ],
    "Psychology": [
      "Introduction to Psychology",
      "Cognitive Psychology",
      "Developmental Psychology",
      "Social Psychology",
      "Abnormal Psychology",
      "Research Methods in Psychology",
      "Behavioral Neuroscience",
      "Clinical Psychology",
      "Educational Psychology",
      "Industrial-Organizational Psychology",
      "Health Psychology",
      "Neuropsychology",
      "Positive Psychology",
      "Forensic Psychology",
      "Industrial Psychology",
      "Child Psychology",
      "Counseling Techniques",
      "Psychopharmacology",
      "Personality Theories",
      "Motivation and Emotion",
      "Psychology Foundations",
      "Psychology Advanced Topics",
      "Psychology Applications",
      "Psychology Techniques",
      "Psychology Seminar",
      "Psychology Workshop",
      "Psychology Research Methods",
      "Psychology Case Studies",
      "Psychology Systems",
      "Psychology Principles",
      "Psychology Innovation",
      "Psychology Design",
      "Psychology Development",
      "Psychology Modeling",
      "Psychology Integration",
      "Psychology Simulation",
      "Psychology Implementation",
      "Psychology Management",
      "Psychology Trends",
      "Psychology Analytics",
      "Psychology Optimization",
      "Psychology Dynamics",
      "Psychology Ethics",
      "Psychology Practices",
      "Psychology Technology",
      "Psychology Engineering",
      "Psychology Performance",
      "Psychology Computing",
      "Psychology Evaluation",
      "Psychology Methodologies"
    ],
    "Biology": [
      "Cell Biology",
      "Genetics",
      "Ecology",
      "Microbiology",
      "Human Anatomy and Physiology",
      "Molecular Biology",
      "Evolutionary Biology",
      "Marine Biology",
      "Botany",
      "Immunology",
      "Biotechnology",
      "Bioinformatics",
      "Conservation Biology",
      "Developmental Biology",
      "Plant Physiology",
      "Animal Behavior",
      "Neurobiology",
      "Virology",
      "Parasitology",
      "Environmental Biology",
      "Biology Foundations",
      "Biology Advanced Topics",
      "Biology Applications",
      "Biology Techniques",
      "Biology Seminar",
      "Biology Workshop",
      "Biology Research Methods",
      "Biology Case Studies",
      "Biology Systems",
      "Biology Principles",
      "Biology Innovation",
      "Biology Design",
      "Biology Development",
      "Biology Modeling",
      "Biology Integration",
      "Biology Simulation",
      "Biology Implementation",
      "Biology Management",
      "Biology Trends",
      "Biology Analytics",
      "Biology Optimization",
      "Biology Dynamics",
      "Biology Ethics",
      "Biology Practices",
      "Biology Technology",
      "Biology Engineering",
      "Biology Performance",
      "Biology Computing",
      "Biology Evaluation",
      "Biology Methodologies"
    ],
    "English Literature": [
      "Introduction to Literature",
      "Shakespeare Studies",
      "Modern Poetry",
      "American Literature",
      "Creative Writing",
      "British Literature",
      "Literary Theory and Criticism",
      "Contemporary Fiction",
      "Victorian Literature",
      "World Literature",
      "Gothic Literature",
      "Postcolonial Literature",
      "Drama and Performance",
      "Literature and Film",
      "Children's Literature",
      "Comparative Literature",
      "Modernist Literature",
      "Romantic Literature",
      "Satire and Humor in Literature",
      "Women's Writing",
      "English Literature Foundations",
      "English Literature Advanced Topics",
      "English Literature Applications",
      "English Literature Techniques",
      "English Literature Seminar",
      "English Literature Workshop",
      "English Literature Research Methods",
      "English Literature Case Studies",
      "English Literature Systems",
      "English Literature Principles",
      "English Literature Innovation",
      "English Literature Design",
      "English Literature Development",
      "English Literature Modeling",
      "English Literature Integration",
      "English Literature Simulation",
      "English Literature Implementation",
      "English Literature Management",
      "English Literature Trends",
      "English Literature Analytics",
      "English Literature Optimization",
      "English Literature Dynamics",
      "English Literature Ethics",
      "English Literature Practices",
      "English Literature Technology",
      "English Literature Engineering",
      "English Literature Performance",
      "English Literature Computing",
      "English Literature Evaluation",
      "English Literature Methodologies"
    ],
    "Chemistry": [
      "General Chemistry",
      "Organic Chemistry I",
      "Organic Chemistry II",
      "Physical Chemistry",
      "Analytical Chemistry",
      "Biochemistry",
      "Inorganic Chemistry",
      "Environmental Chemistry",
      "Medicinal Chemistry",
      "Polymer Chemistry",
      "Industrial Chemistry",
      "Electrochemistry",
      "Green Chemistry",
      "Spectroscopy",
      "Chemical Kinetics",
      "Surface Chemistry",
      "Quantum Chemistry",
      "Materials Chemistry",
      "Organometallic Chemistry",
      "Forensic Chemistry",
      "Chemistry Foundations",
      "Chemistry Advanced Topics",
      "Chemistry Applications",
      "Chemistry Techniques",
      "Chemistry Seminar",
      "Chemistry Workshop",
      "Chemistry Research Methods",
      "Chemistry Case Studies",
      "Chemistry Systems",
      "Chemistry Principles",
      "Chemistry Innovation",
      "Chemistry Design",
      "Chemistry Development",
      "Chemistry Modeling",
      "Chemistry Integration",
      "Chemistry Simulation",
      "Chemistry Implementation",
      "Chemistry Management",
      "Chemistry Trends",
      "Chemistry Analytics",
      "Chemistry Optimization",
      "Chemistry Dynamics",
      "Chemistry Ethics",
      "Chemistry Practices",
      "Chemistry Technology",
      "Chemistry Engineering",
      "Chemistry Performance",
      "Chemistry Computing",
      "Chemistry Evaluation",
      "Chemistry Methodologies"
    ],
    "Engineering": [
      "Engineering Mechanics",
      "Circuit Analysis",
      "Materials Science",
      "Thermodynamics for Engineers",
      "Computer-Aided Design",
      "Fluid Mechanics",
      "Control Systems",
      "Digital Electronics",
      "Engineering Mathematics",
      "Project Management for Engineers",
      "Structural Dynamics",
      "Mechanical Design",
      "Robotics",
      "Embedded Systems for Engineers",
      "Renewable Energy Engineering",
      "Heat Transfer",
      "Mechatronics",
      "Industrial Automation",
      "Transportation Engineering",
      "Engineering Ethics",
      "Engineering Foundations",
      "Engineering Advanced Topics",
      "Engineering Applications",
      "Engineering Techniques",
      "Engineering Seminar",
      "Engineering Workshop",
      "Engineering Research Methods",
      "Engineering Case Studies",
      "Engineering Systems",
      "Engineering Principles",
      "Engineering Innovation",
      "Engineering Design",
      "Engineering Development",
      "Engineering Modeling",
      "Engineering Integration",
      "Engineering Simulation",
      "Engineering Implementation",
      "Engineering Management",
      "Engineering Trends",
      "Engineering Analytics",
      "Engineering Optimization",
      "Engineering Dynamics",
      "Engineering Ethics",
      "Engineering Practices",
      "Engineering Technology",
      "Engineering Engineering",
      "Engineering Performance",
      "Engineering Computing",
      "Engineering Evaluation",
      "Engineering Methodologies"
    ],
    "History": [
      "World History",
      "American History",
      "European History",
      "Ancient Civilizations",
      "Contemporary History",
      "Medieval History",
      "History of World Wars",
      "Asian History",
      "African History",
      "Latin American History",
      "History of Science and Technology",
      "Colonial History",
      "History of Religion",
      "Modern European History",
      "Middle Eastern History",
      "History of Political Movements",
      "Economic History",
      "History of Art and Culture",
      "History of Education",
      "Globalization and History",
      "History Foundations",
      "History Advanced Topics",
      "History Applications",
      "History Techniques",
      "History Seminar",
      "History Workshop",
      "History Research Methods",
      "History Case Studies",
      "History Systems",
      "History Principles",
      "History Innovation",
      "History Design",
      "History Development",
      "History Modeling",
      "History Integration",
      "History Simulation",
      "History Implementation",
      "History Management",
      "History Trends",
      "History Analytics",
      "History Optimization",
      "History Dynamics",
      "History Ethics",
      "History Practices",
      "History Technology",
      "History Engineering",
      "History Performance",
      "History Computing",
      "History Evaluation",
      "History Methodologies"
    ],
    "Economics": [
      "Microeconomics",
      "Macroeconomics",
      "Econometrics",
      "International Economics",
      "Development Economics",
      "Labor Economics",
      "Public Economics",
      "Financial Economics",
      "Game Theory",
      "Economic History",
      "Behavioral Economics",
      "Health Economics",
      "Environmental Economics",
      "Industrial Organization",
      "Monetary Economics",
      "International Trade Policy",
      "Development Policy",
      "Urban Economics",
      "Energy Economics",
      "Agricultural Economics",
      "Economics Foundations",
      "Economics Advanced Topics",
      "Economics Applications",
      "Economics Techniques",
      "Economics Seminar",
      "Economics Workshop",
      "Economics Research Methods",
      "Economics Case Studies",
      "Economics Systems",
      "Economics Principles",
      "Economics Innovation",
      "Economics Design",
      "Economics Development",
      "Economics Modeling",
      "Economics Integration",
      "Economics Simulation",
      "Economics Implementation",
      "Economics Management",
      "Economics Trends",
      "Economics Analytics",
      "Economics Optimization",
      "Economics Dynamics",
      "Economics Ethics",
      "Economics Practices",
      "Economics Technology",
      "Economics Engineering",
      "Economics Performance",
      "Economics Computing",
      "Economics Evaluation",
      "Economics Methodologies"
    ],
    "Political Science": [
      "Introduction to Political Science",
      "Comparative Politics",
      "International Relations",
      "Political Theory",
      "Public Policy",
      "American Government",
      "Constitutional Law",
      "Political Economy",
      "Global Governance",
      "Research Methods in Political Science",
      "Political Parties and Elections",
      "Diplomacy and Negotiation",
      "Human Rights and Politics",
      "Security Studies",
      "International Organizations",
      "Conflict Resolution",
      "Policy Analysis",
      "Political Philosophy",
      "Governance and Ethics",
      "Political Communication",
      "Political Science Foundations",
      "Political Science Advanced Topics",
      "Political Science Applications",
      "Political Science Techniques",
      "Political Science Seminar",
      "Political Science Workshop",
      "Political Science Research Methods",
      "Political Science Case Studies",
      "Political Science Systems",
      "Political Science Principles",
      "Political Science Innovation",
      "Political Science Design",
      "Political Science Development",
      "Political Science Modeling",
      "Political Science Integration",
      "Political Science Simulation",
      "Political Science Implementation",
      "Political Science Management",
      "Political Science Trends",
      "Political Science Analytics",
      "Political Science Optimization",
      "Political Science Dynamics",
      "Political Science Ethics",
      "Political Science Practices",
      "Political Science Technology",
      "Political Science Engineering",
      "Political Science Performance",
      "Political Science Computing",
      "Political Science Evaluation",
      "Political Science Methodologies"
    ],
    "Sociology": [
      "Introduction to Sociology",
      "Social Theory",
      "Research Methods in Sociology",
      "Urban Sociology",
      "Sociology of Gender",
      "Race and Ethnicity",
      "Criminology",
      "Social Stratification",
      "Medical Sociology",
      "Environmental Sociology",
      "Sociology of Religion",
      "Sociology of Education",
      "Family and Society",
      "Sociology of Work",
      "Globalization and Society",
      "Sociology of Media",
      "Social Movements",
      "Political Sociology",
      "Community Development",
      "Sociology of Aging",
      "Sociology Foundations",
      "Sociology Advanced Topics",
      "Sociology Applications",
      "Sociology Techniques",
      "Sociology Seminar",
      "Sociology Workshop",
      "Sociology Research Methods",
      "Sociology Case Studies",
      "Sociology Systems",
      "Sociology Principles",
      "Sociology Innovation",
      "Sociology Design",
      "Sociology Development",
      "Sociology Modeling",
      "Sociology Integration",
      "Sociology Simulation",
      "Sociology Implementation",
      "Sociology Management",
      "Sociology Trends",
      "Sociology Analytics",
      "Sociology Optimization",
      "Sociology Dynamics",
      "Sociology Ethics",
      "Sociology Practices",
      "Sociology Technology",
      "Sociology Engineering",
      "Sociology Performance",
      "Sociology Computing",
      "Sociology Evaluation",
      "Sociology Methodologies"
    ],
    "Art and Design": [
      "Drawing Fundamentals",
      "Painting Techniques",
      "Graphic Design",
      "Digital Art",
      "Art History",
      "Sculpture",
      "Photography",
      "Typography",
      "3D Modeling",
      "Visual Communication",
      "Illustration",
      "Animation",
      "Fashion Design",
      "Interior Design",
      "Printmaking",
      "Web Design",
      "Concept Art",
      "Design Thinking",
      "Video Production",
      "Creative Portfolio Development",
      "Art and Design Foundations",
      "Art and Design Advanced Topics",
      "Art and Design Applications",
      "Art and Design Techniques",
      "Art and Design Seminar",
      "Art and Design Workshop",
      "Art and Design Research Methods",
      "Art and Design Case Studies",
      "Art and Design Systems",
      "Art and Design Principles",
      "Art and Design Innovation",
      "Art and Design Design",
      "Art and Design Development",
      "Art and Design Modeling",
      "Art and Design Integration",
      "Art and Design Simulation",
      "Art and Design Implementation",
      "Art and Design Management",
      "Art and Design Trends",
      "Art and Design Analytics",
      "Art and Design Optimization",
      "Art and Design Dynamics",
      "Art and Design Ethics",
      "Art and Design Practices",
      "Art and Design Technology",
      "Art and Design Engineering",
      "Art and Design Performance",
      "Art and Design Computing",
      "Art and Design Evaluation",
      "Art and Design Methodologies"
    ],
    "Music": [
      "Music Theory I",
      "Music Theory II",
      "Music History",
      "Ear Training",
      "Piano Performance",
      "Vocal Performance",
      "Composition",
      "Music Production",
      "Jazz Studies",
      "World Music",
      "Conducting",
      "Music Technology",
      "Orchestration",
      "Guitar Performance",
      "Music Pedagogy",
      "Ethnomusicology",
      "Choral Studies",
      "Music Appreciation",
      "Film Scoring",
      "Advanced Improvisation",
      "Music Foundations",
      "Music Advanced Topics",
      "Music Applications",
      "Music Techniques",
      "Music Seminar",
      "Music Workshop",
      "Music Research Methods",
      "Music Case Studies",
      "Music Systems",
      "Music Principles",
      "Music Innovation",
      "Music Design",
      "Music Development",
      "Music Modeling",
      "Music Integration",
      "Music Simulation",
      "Music Implementation",
      "Music Management",
      "Music Trends",
      "Music Analytics",
      "Music Optimization",
      "Music Dynamics",
      "Music Ethics",
      "Music Practices",
      "Music Technology",
      "Music Engineering",
      "Music Performance",
      "Music Computing",
      "Music Evaluation",
      "Music Methodologies"
    ],
    "Philosophy": [
      "Introduction to Philosophy",
      "Ethics",
      "Logic",
      "Metaphysics",
      "Epistemology",
      "Philosophy of Mind",
      "Political Philosophy",
      "Philosophy of Science",
      "Existentialism",
      "Eastern Philosophy",
      "Philosophy of Religion",
      "Aesthetics",
      "Environmental Philosophy",
      "Philosophy of Law",
      "Feminist Philosophy",
      "Social and Political Philosophy",
      "Phenomenology",
      "Moral Philosophy",
      "Philosophy of Language",
      "Philosophy of Technology",
      "Philosophy Foundations",
      "Philosophy Advanced Topics",
      "Philosophy Applications",
      "Philosophy Techniques",
      "Philosophy Seminar",
      "Philosophy Workshop",
      "Philosophy Research Methods",
      "Philosophy Case Studies",
      "Philosophy Systems",
      "Philosophy Principles",
      "Philosophy Innovation",
      "Philosophy Design",
      "Philosophy Development",
      "Philosophy Modeling",
      "Philosophy Integration",
      "Philosophy Simulation",
      "Philosophy Implementation",
      "Philosophy Management",
      "Philosophy Trends",
      "Philosophy Analytics",
      "Philosophy Optimization",
      "Philosophy Dynamics",
      "Philosophy Ethics",
      "Philosophy Practices",
      "Philosophy Technology",
      "Philosophy Engineering",
      "Philosophy Performance",
      "Philosophy Computing",
      "Philosophy Evaluation",
      "Philosophy Methodologies"
    ],
    "Environmental Science": [
      "Introduction to Environmental Science",
      "Ecology and Conservation",
      "Climate Change",
      "Environmental Policy",
      "Sustainable Development",
      "Water Resources Management",
      "Air Quality and Pollution",
      "Environmental Impact Assessment",
      "Renewable Energy",
      "Wildlife Conservation",
      "Soil Science",
      "Environmental Chemistry",
      "Urban Ecology",
      "Marine Conservation",
      "Forest Management",
      "Environmental Geology",
      "Resource Economics",
      "Environmental Law",
      "Natural Resource Management",
      "Ecosystem Services",
      "Environmental Science Foundations",
      "Environmental Science Advanced Topics",
      "Environmental Science Applications",
      "Environmental Science Techniques",
      "Environmental Science Seminar",
      "Environmental Science Workshop",
      "Environmental Science Research Methods",
      "Environmental Science Case Studies",
      "Environmental Science Systems",
      "Environmental Science Principles",
      "Environmental Science Innovation",
      "Environmental Science Design",
      "Environmental Science Development",
      "Environmental Science Modeling",
      "Environmental Science Integration",
      "Environmental Science Simulation",
      "Environmental Science Implementation",
      "Environmental Science Management",
      "Environmental Science Trends",
      "Environmental Science Analytics",
      "Environmental Science Optimization",
      "Environmental Science Dynamics",
      "Environmental Science Ethics",
      "Environmental Science Practices",
      "Environmental Science Technology",
      "Environmental Science Engineering",
      "Environmental Science Performance",
      "Environmental Science Computing",
      "Environmental Science Evaluation",
      "Environmental Science Methodologies"
    ],
    "Law": [
      "Introduction to Law",
      "Constitutional Law",
      "Criminal Law",
      "Contract Law",
      "Tort Law",
      "Property Law",
      "Corporate Law",
      "International Law",
      "Legal Research and Writing",
      "Human Rights Law",
      "Intellectual Property Law",
      "Family Law",
      "Environmental Law",
      "Labour Law",
      "Tax Law",
      "Comparative Law",
      "Civil Procedure",
      "Evidence Law",
      "Administrative Law",
      "Cyber Law",
      "Law Foundations",
      "Law Advanced Topics",
      "Law Applications",
      "Law Techniques",
      "Law Seminar",
      "Law Workshop",
      "Law Research Methods",
      "Law Case Studies",
      "Law Systems",
      "Law Principles",
      "Law Innovation",
      "Law Design",
      "Law Development",
      "Law Modeling",
      "Law Integration",
      "Law Simulation",
      "Law Implementation",
      "Law Management",
      "Law Trends",
      "Law Analytics",
      "Law Optimization",
      "Law Dynamics",
      "Law Ethics",
      "Law Practices",
      "Law Technology",
      "Law Engineering",
      "Law Performance",
      "Law Computing",
      "Law Evaluation",
      "Law Methodologies"
    ],
    "Medicine": [
      "Human Anatomy",
      "Physiology",
      "Pathology",
      "Pharmacology",
      "Biochemistry for Medical Students",
      "Medical Ethics",
      "Clinical Skills",
      "Surgery Fundamentals",
      "Internal Medicine",
      "Public Health",
      "Microbiology for Medicine",
      "Immunology",
      "Pediatrics",
      "Obstetrics and Gynecology",
      "Radiology",
      "Emergency Medicine",
      "Psychiatry",
      "Dermatology",
      "Geriatric Medicine",
      "Neurology",
      "Medicine Foundations",
      "Medicine Advanced Topics",
      "Medicine Applications",
      "Medicine Techniques",
      "Medicine Seminar",
      "Medicine Workshop",
      "Medicine Research Methods",
      "Medicine Case Studies",
      "Medicine Systems",
      "Medicine Principles",
      "Medicine Innovation",
      "Medicine Design",
      "Medicine Development",
      "Medicine Modeling",
      "Medicine Integration",
      "Medicine Simulation",
      "Medicine Implementation",
      "Medicine Management",
      "Medicine Trends",
      "Medicine Analytics",
      "Medicine Optimization",
      "Medicine Dynamics",
      "Medicine Ethics",
      "Medicine Practices",
      "Medicine Technology",
      "Medicine Engineering",
      "Medicine Performance",
      "Medicine Computing",
      "Medicine Evaluation",
      "Medicine Methodologies"
    ],
    "Civil Engineering": [
      "Structural Analysis",
      "Geotechnical Engineering",
      "Transportation Engineering",
      "Hydraulic Engineering",
      "Construction Management",
      "Environmental Engineering",
      "Surveying",
      "Steel Structures",
      "Concrete Technology",
      "Urban Planning",
      "Soil Mechanics",
      "Bridge Engineering",
      "Construction Materials",
      "Foundation Engineering",
      "Highway Engineering",
      "Structural Dynamics",
      "Water Resource Engineering",
      "Earthquake Engineering",
      "Project Scheduling",
      "Environmental Impact in Civil Projects",
      "Civil Engineering Foundations",
      "Civil Engineering Advanced Topics",
      "Civil Engineering Applications",
      "Civil Engineering Techniques",
      "Civil Engineering Seminar",
      "Civil Engineering Workshop",
      "Civil Engineering Research Methods",
      "Civil Engineering Case Studies",
      "Civil Engineering Systems",
      "Civil Engineering Principles",
      "Civil Engineering Innovation",
      "Civil Engineering Design",
      "Civil Engineering Development",
      "Civil Engineering Modeling",
      "Civil Engineering Integration",
      "Civil Engineering Simulation",
      "Civil Engineering Implementation",
      "Civil Engineering Management",
      "Civil Engineering Trends",
      "Civil Engineering Analytics",
      "Civil Engineering Optimization",
      "Civil Engineering Dynamics",
      "Civil Engineering Ethics",
      "Civil Engineering Practices",
      "Civil Engineering Technology",
      "Civil Engineering Engineering",
      "Civil Engineering Performance",
      "Civil Engineering Computing",
      "Civil Engineering Evaluation",
      "Civil Engineering Methodologies"
    ],
    "Architecture": [
      "Architecture Foundations",
      "Architecture Advanced Topics",
      "Architecture Applications",
      "Architecture Techniques",
      "Architecture Seminar",
      "Architecture Workshop",
      "Architecture Research Methods",
      "Architecture Case Studies",
      "Architecture Systems",
      "Architecture Principles",
      "Architecture Innovation",
      "Architecture Design",
      "Architecture Development",
      "Architecture Modeling",
      "Architecture Integration",
      "Architecture Simulation",
      "Architecture Implementation",
      "Architecture Management",
      "Architecture Trends",
      "Architecture Analytics",
      "Architecture Optimization",
      "Architecture Dynamics",
      "Architecture Ethics",
      "Architecture Practices",
      "Architecture Technology",
      "Architecture Engineering",
      "Architecture Performance",
      "Architecture Computing",
      "Architecture Evaluation",
      "Architecture Methodologies"
    ],
    "Astronomy": [
      "Astronomy Foundations",
      "Astronomy Advanced Topics",
      "Astronomy Applications",
      "Astronomy Techniques",
      "Astronomy Seminar",
      "Astronomy Workshop",
      "Astronomy Research Methods",
      "Astronomy Case Studies",
      "Astronomy Systems",
      "Astronomy Principles",
      "Astronomy Innovation",
      "Astronomy Design",
      "Astronomy Development",
      "Astronomy Modeling",
      "Astronomy Integration",
      "Astronomy Simulation",
      "Astronomy Implementation",
      "Astronomy Management",
      "Astronomy Trends",
      "Astronomy Analytics",
      "Astronomy Optimization",
      "Astronomy Dynamics",
      "Astronomy Ethics",
      "Astronomy Practices",
      "Astronomy Technology",
      "Astronomy Engineering",
      "Astronomy Performance",
      "Astronomy Computing",
      "Astronomy Evaluation",
      "Astronomy Methodologies"
    ],
    "Marine Science": [
      "Marine Science Foundations",
      "Marine Science Advanced Topics",
      "Marine Science Applications",
      "Marine Science Techniques",
      "Marine Science Seminar",
      "Marine Science Workshop",
      "Marine Science Research Methods",
      "Marine Science Case Studies",
      "Marine Science Systems",
      "Marine Science Principles",
      "Marine Science Innovation",
      "Marine Science Design",
      "Marine Science Development",
      "Marine Science Modeling",
      "Marine Science Integration",
      "Marine Science Simulation",
      "Marine Science Implementation",
      "Marine Science Management",
      "Marine Science Trends",
      "Marine Science Analytics",
      "Marine Science Optimization",
      "Marine Science Dynamics",
      "Marine Science Ethics",
      "Marine Science Practices",
      "Marine Science Technology",
      "Marine Science Engineering",
      "Marine Science Performance",
      "Marine Science Computing",
      "Marine Science Evaluation",
      "Marine Science Methodologies"
    ],
    "Linguistics": [
      "Linguistics Foundations",
      "Linguistics Advanced Topics",
      "Linguistics Applications",
      "Linguistics Techniques",
      "Linguistics Seminar",
      "Linguistics Workshop",
      "Linguistics Research Methods",
      "Linguistics Case Studies",
      "Linguistics Systems",
      "Linguistics Principles",
      "Linguistics Innovation",
      "Linguistics Design",
      "Linguistics Development",
      "Linguistics Modeling",
      "Linguistics Integration",
      "Linguistics Simulation",
      "Linguistics Implementation",
      "Linguistics Management",
      "Linguistics Trends",
      "Linguistics Analytics",
      "Linguistics Optimization",
      "Linguistics Dynamics",
      "Linguistics Ethics",
      "Linguistics Practices",
      "Linguistics Technology",
      "Linguistics Engineering",
      "Linguistics Performance",
      "Linguistics Computing",
      "Linguistics Evaluation",
      "Linguistics Methodologies"
    ],
    "Anthropology": [
      "Anthropology Foundations",
      "Anthropology Advanced Topics",
      "Anthropology Applications",
      "Anthropology Techniques",
      "Anthropology Seminar",
      "Anthropology Workshop",
      "Anthropology Research Methods",
      "Anthropology Case Studies",
      "Anthropology Systems",
      "Anthropology Principles",
      "Anthropology Innovation",
      "Anthropology Design",
      "Anthropology Development",
      "Anthropology Modeling",
      "Anthropology Integration",
      "Anthropology Simulation",
      "Anthropology Implementation",
      "Anthropology Management",
      "Anthropology Trends",
      "Anthropology Analytics",
      "Anthropology Optimization",
      "Anthropology Dynamics",
      "Anthropology Ethics",
      "Anthropology Practices",
      "Anthropology Technology",
      "Anthropology Engineering",
      "Anthropology Performance",
      "Anthropology Computing",
      "Anthropology Evaluation",
      "Anthropology Methodologies"
    ],
    "Geology": [
      "Geology Foundations",
      "Geology Advanced Topics",
      "Geology Applications",
      "Geology Techniques",
      "Geology Seminar",
      "Geology Workshop",
      "Geology Research Methods",
      "Geology Case Studies",
      "Geology Systems",
      "Geology Principles",
      "Geology Innovation",
      "Geology Design",
      "Geology Development",
      "Geology Modeling",
      "Geology Integration",
      "Geology Simulation",
      "Geology Implementation",
      "Geology Management",
      "Geology Trends",
      "Geology Analytics",
      "Geology Optimization",
      "Geology Dynamics",
      "Geology Ethics",
      "Geology Practices",
      "Geology Technology",
      "Geology Engineering",
      "Geology Performance",
      "Geology Computing",
      "Geology Evaluation",
      "Geology Methodologies"
    ],
    "Education": [
      "Education Foundations",
      "Education Advanced Topics",
      "Education Applications",
      "Education Techniques",
      "Education Seminar",
      "Education Workshop",
      "Education Research Methods",
      "Education Case Studies",
      "Education Systems",
      "Education Principles",
      "Education Innovation",
      "Education Design",
      "Education Development",
      "Education Modeling",
      "Education Integration",
      "Education Simulation",
      "Education Implementation",
      "Education Management",
      "Education Trends",
      "Education Analytics",
      "Education Optimization",
      "Education Dynamics",
      "Education Ethics",
      "Education Practices",
      "Education Technology",
      "Education Engineering",
      "Education Performance",
      "Education Computing",
      "Education Evaluation",
      "Education Methodologies"
    ],
    "Public Health": [
      "Public Health Foundations",
      "Public Health Advanced Topics",
      "Public Health Applications",
      "Public Health Techniques",
      "Public Health Seminar",
      "Public Health Workshop",
      "Public Health Research Methods",
      "Public Health Case Studies",
      "Public Health Systems",
      "Public Health Principles",
      "Public Health Innovation",
      "Public Health Design",
      "Public Health Development",
      "Public Health Modeling",
      "Public Health Integration",
      "Public Health Simulation",
      "Public Health Implementation",
      "Public Health Management",
      "Public Health Trends",
      "Public Health Analytics",
      "Public Health Optimization",
      "Public Health Dynamics",
      "Public Health Ethics",
      "Public Health Practices",
      "Public Health Technology",
      "Public Health Engineering",
      "Public Health Performance",
      "Public Health Computing",
      "Public Health Evaluation",
      "Public Health Methodologies"
    ],
    "Tourism Management": [
      "Tourism Management Foundations",
      "Tourism Management Advanced Topics",
      "Tourism Management Applications",
      "Tourism Management Techniques",
      "Tourism Management Seminar",
      "Tourism Management Workshop",
      "Tourism Management Research Methods",
      "Tourism Management Case Studies",
      "Tourism Management Systems",
      "Tourism Management Principles",
      "Tourism Management Innovation",
      "Tourism Management Design",
      "Tourism Management Development",
      "Tourism Management Modeling",
      "Tourism Management Integration",
      "Tourism Management Simulation",
      "Tourism Management Implementation",
      "Tourism Management Management",
      "Tourism Management Trends",
      "Tourism Management Analytics",
      "Tourism Management Optimization",
      "Tourism Management Dynamics",
      "Tourism Management Ethics",
      "Tourism Management Practices",
      "Tourism Management Technology",
      "Tourism Management Engineering",
      "Tourism Management Performance",
      "Tourism Management Computing",
      "Tourism Management Evaluation",
      "Tourism Management Methodologies"
    ],
    "Graphic Design": [
      "Graphic Design Foundations",
      "Graphic Design Advanced Topics",
      "Graphic Design Applications",
      "Graphic Design Techniques",
      "Graphic Design Seminar",
      "Graphic Design Workshop",
      "Graphic Design Research Methods",
      "Graphic Design Case Studies",
      "Graphic Design Systems",
      "Graphic Design Principles",
      "Graphic Design Innovation",
      "Graphic Design Design",
      "Graphic Design Development",
      "Graphic Design Modeling",
      "Graphic Design Integration",
      "Graphic Design Simulation",
      "Graphic Design Implementation",
      "Graphic Design Management",
      "Graphic Design Trends",
      "Graphic Design Analytics",
      "Graphic Design Optimization",
      "Graphic Design Dynamics",
      "Graphic Design Ethics",
      "Graphic Design Practices",
      "Graphic Design Technology",
      "Graphic Design Engineering",
      "Graphic Design Performance",
      "Graphic Design Computing",
      "Graphic Design Evaluation",
      "Graphic Design Methodologies"
    ],
    "Agricultural Science": [
      "Agricultural Science Foundations",
      "Agricultural Science Advanced Topics",
      "Agricultural Science Applications",
      "Agricultural Science Techniques",
      "Agricultural Science Seminar",
      "Agricultural Science Workshop",
      "Agricultural Science Research Methods",
      "Agricultural Science Case Studies",
      "Agricultural Science Systems",
      "Agricultural Science Principles",
      "Agricultural Science Innovation",
      "Agricultural Science Design",
      "Agricultural Science Development",
      "Agricultural Science Modeling",
      "Agricultural Science Integration",
      "Agricultural Science Simulation",
      "Agricultural Science Implementation",
      "Agricultural Science Management",
      "Agricultural Science Trends",
      "Agricultural Science Analytics",
      "Agricultural Science Optimization",
      "Agricultural Science Dynamics",
      "Agricultural Science Ethics",
      "Agricultural Science Practices",
      "Agricultural Science Technology",
      "Agricultural Science Engineering",
      "Agricultural Science Performance",
      "Agricultural Science Computing",
      "Agricultural Science Evaluation",
      "Agricultural Science Methodologies"
    ],
    "Information Systems": [
      "Information Systems Foundations",
      "Information Systems Advanced Topics",
      "Information Systems Applications",
      "Information Systems Techniques",
      "Information Systems Seminar",
      "Information Systems Workshop",
      "Information Systems Research Methods",
      "Information Systems Case Studies",
      "Information Systems Systems",
      "Information Systems Principles",
      "Information Systems Innovation",
      "Information Systems Design",
      "Information Systems Development",
      "Information Systems Modeling",
      "Information Systems Integration",
      "Information Systems Simulation",
      "Information Systems Implementation",
      "Information Systems Management",
      "Information Systems Trends",
      "Information Systems Analytics",
      "Information Systems Optimization",
      "Information Systems Dynamics",
      "Information Systems Ethics",
      "Information Systems Practices",
      "Information Systems Technology",
      "Information Systems Engineering",
      "Information Systems Performance",
      "Information Systems Computing",
      "Information Systems Evaluation",
      "Information Systems Methodologies"
    ],
    "Criminal Justice": [
      "Criminal Justice Foundations",
      "Criminal Justice Advanced Topics",
      "Criminal Justice Applications",
      "Criminal Justice Techniques",
      "Criminal Justice Seminar",
      "Criminal Justice Workshop",
      "Criminal Justice Research Methods",
      "Criminal Justice Case Studies",
      "Criminal Justice Systems",
      "Criminal Justice Principles",
      "Criminal Justice Innovation",
      "Criminal Justice Design",
      "Criminal Justice Development",
      "Criminal Justice Modeling",
      "Criminal Justice Integration",
      "Criminal Justice Simulation",
      "Criminal Justice Implementation",
      "Criminal Justice Management",
      "Criminal Justice Trends",
      "Criminal Justice Analytics",
      "Criminal Justice Optimization",
      "Criminal Justice Dynamics",
      "Criminal Justice Ethics",
      "Criminal Justice Practices",
      "Criminal Justice Technology",
      "Criminal Justice Engineering",
      "Criminal Justice Performance",
      "Criminal Justice Computing",
      "Criminal Justice Evaluation",
      "Criminal Justice Methodologies"
    ],
    "Media Studies": [
      "Media Studies Foundations",
      "Media Studies Advanced Topics",
      "Media Studies Applications",
      "Media Studies Techniques",
      "Media Studies Seminar",
      "Media Studies Workshop",
      "Media Studies Research Methods",
      "Media Studies Case Studies",
      "Media Studies Systems",
      "Media Studies Principles",
      "Media Studies Innovation",
      "Media Studies Design",
      "Media Studies Development",
      "Media Studies Modeling",
      "Media Studies Integration",
      "Media Studies Simulation",
      "Media Studies Implementation",
      "Media Studies Management",
      "Media Studies Trends",
      "Media Studies Analytics",
      "Media Studies Optimization",
      "Media Studies Dynamics",
      "Media Studies Ethics",
      "Media Studies Practices",
      "Media Studies Technology",
      "Media Studies Engineering",
      "Media Studies Performance",
      "Media Studies Computing",
      "Media Studies Evaluation",
      "Media Studies Methodologies"
    ],
    "Theatre Arts": [
      "Theatre Arts Foundations",
      "Theatre Arts Advanced Topics",
      "Theatre Arts Applications",
      "Theatre Arts Techniques",
      "Theatre Arts Seminar",
      "Theatre Arts Workshop",
      "Theatre Arts Research Methods",
      "Theatre Arts Case Studies",
      "Theatre Arts Systems",
      "Theatre Arts Principles",
      "Theatre Arts Innovation",
      "Theatre Arts Design",
      "Theatre Arts Development",
      "Theatre Arts Modeling",
      "Theatre Arts Integration",
      "Theatre Arts Simulation",
      "Theatre Arts Implementation",
      "Theatre Arts Management",
      "Theatre Arts Trends",
      "Theatre Arts Analytics",
      "Theatre Arts Optimization",
      "Theatre Arts Dynamics",
      "Theatre Arts Ethics",
      "Theatre Arts Practices",
      "Theatre Arts Technology",
      "Theatre Arts Engineering",
      "Theatre Arts Performance",
      "Theatre Arts Computing",
      "Theatre Arts Evaluation",
      "Theatre Arts Methodologies"
    ],
    "Data Science": [
      "Data Science Foundations",
      "Data Science Advanced Topics",
      "Data Science Applications",
      "Data Science Techniques",
      "Data Science Seminar",
      "Data Science Workshop",
      "Data Science Research Methods",
      "Data Science Case Studies",
      "Data Science Systems",
      "Data Science Principles",
      "Data Science Innovation",
      "Data Science Design",
      "Data Science Development",
      "Data Science Modeling",
      "Data Science Integration",
      "Data Science Simulation",
      "Data Science Implementation",
      "Data Science Management",
      "Data Science Trends",
      "Data Science Analytics",
      "Data Science Optimization",
      "Data Science Dynamics",
      "Data Science Ethics",
      "Data Science Practices",
      "Data Science Technology",
      "Data Science Engineering",
      "Data Science Performance",
      "Data Science Computing",
      "Data Science Evaluation",
      "Data Science Methodologies"
    ],
    "Cybersecurity Engineering": [
      "Cybersecurity Engineering Foundations",
      "Cybersecurity Engineering Advanced Topics",
      "Cybersecurity Engineering Applications",
      "Cybersecurity Engineering Techniques",
      "Cybersecurity Engineering Seminar",
      "Cybersecurity Engineering Workshop",
      "Cybersecurity Engineering Research Methods",
      "Cybersecurity Engineering Case Studies",
      "Cybersecurity Engineering Systems",
      "Cybersecurity Engineering Principles",
      "Cybersecurity Engineering Innovation",
      "Cybersecurity Engineering Design",
      "Cybersecurity Engineering Development",
      "Cybersecurity Engineering Modeling",
      "Cybersecurity Engineering Integration",
      "Cybersecurity Engineering Simulation",
      "Cybersecurity Engineering Implementation",
      "Cybersecurity Engineering Management",
      "Cybersecurity Engineering Trends",
      "Cybersecurity Engineering Analytics",
      "Cybersecurity Engineering Optimization",
      "Cybersecurity Engineering Dynamics",
      "Cybersecurity Engineering Ethics",
      "Cybersecurity Engineering Practices",
      "Cybersecurity Engineering Technology",
      "Cybersecurity Engineering Engineering",
      "Cybersecurity Engineering Performance",
      "Cybersecurity Engineering Computing",
      "Cybersecurity Engineering Evaluation",
      "Cybersecurity Engineering Methodologies"
    ],
    "Artificial Intelligence Engineering": [
      "Artificial Intelligence Engineering Foundations",
      "Artificial Intelligence Engineering Advanced Topics",
      "Artificial Intelligence Engineering Applications",
      "Artificial Intelligence Engineering Techniques",
      "Artificial Intelligence Engineering Seminar",
      "Artificial Intelligence Engineering Workshop",
      "Artificial Intelligence Engineering Research Methods",
      "Artificial Intelligence Engineering Case Studies",
      "Artificial Intelligence Engineering Systems",
      "Artificial Intelligence Engineering Principles",
      "Artificial Intelligence Engineering Innovation",
      "Artificial Intelligence Engineering Design",
      "Artificial Intelligence Engineering Development",
      "Artificial Intelligence Engineering Modeling",
      "Artificial Intelligence Engineering Integration",
      "Artificial Intelligence Engineering Simulation",
      "Artificial Intelligence Engineering Implementation",
      "Artificial Intelligence Engineering Management",
      "Artificial Intelligence Engineering Trends",
      "Artificial Intelligence Engineering Analytics",
      "Artificial Intelligence Engineering Optimization",
      "Artificial Intelligence Engineering Dynamics",
      "Artificial Intelligence Engineering Ethics",
      "Artificial Intelligence Engineering Practices",
      "Artificial Intelligence Engineering Technology",
      "Artificial Intelligence Engineering Engineering",
      "Artificial Intelligence Engineering Performance",
      "Artificial Intelligence Engineering Computing",
      "Artificial Intelligence Engineering Evaluation",
      "Artificial Intelligence Engineering Methodologies"
    ],
    "Nanotechnology": [
      "Nanotechnology Foundations",
      "Nanotechnology Advanced Topics",
      "Nanotechnology Applications",
      "Nanotechnology Techniques",
      "Nanotechnology Seminar",
      "Nanotechnology Workshop",
      "Nanotechnology Research Methods",
      "Nanotechnology Case Studies",
      "Nanotechnology Systems",
      "Nanotechnology Principles",
      "Nanotechnology Innovation",
      "Nanotechnology Design",
      "Nanotechnology Development",
      "Nanotechnology Modeling",
      "Nanotechnology Integration",
      "Nanotechnology Simulation",
      "Nanotechnology Implementation",
      "Nanotechnology Management",
      "Nanotechnology Trends",
      "Nanotechnology Analytics",
      "Nanotechnology Optimization",
      "Nanotechnology Dynamics",
      "Nanotechnology Ethics",
      "Nanotechnology Practices",
      "Nanotechnology Technology",
      "Nanotechnology Engineering",
      "Nanotechnology Performance",
      "Nanotechnology Computing",
      "Nanotechnology Evaluation",
      "Nanotechnology Methodologies"
    ],
    "Biotechnology": [
      "Biotechnology Foundations",
      "Biotechnology Advanced Topics",
      "Biotechnology Applications",
      "Biotechnology Techniques",
      "Biotechnology Seminar",
      "Biotechnology Workshop",
      "Biotechnology Research Methods",
      "Biotechnology Case Studies",
      "Biotechnology Systems",
      "Biotechnology Principles",
      "Biotechnology Innovation",
      "Biotechnology Design",
      "Biotechnology Development",
      "Biotechnology Modeling",
      "Biotechnology Integration",
      "Biotechnology Simulation",
      "Biotechnology Implementation",
      "Biotechnology Management",
      "Biotechnology Trends",
      "Biotechnology Analytics",
      "Biotechnology Optimization",
      "Biotechnology Dynamics",
      "Biotechnology Ethics",
      "Biotechnology Practices",
      "Biotechnology Technology",
      "Biotechnology Engineering",
      "Biotechnology Performance",
      "Biotechnology Computing",
      "Biotechnology Evaluation",
      "Biotechnology Methodologies"
    ]
  },
  "club_names": [
    "Chess Club",
    "Drama Club",
    "Debate Team",
    "Photography Club",
    "Coding Club",
    "Robotics Team",
    "Music Band",
    "Art Society",
    "Sports Club",
    "Yoga Group",
    "Book Club",
    "Film Society",
    "Volunteer Group",
    "Environmental Club",
    "Dance Team",
    "Gaming Club",
    "Science Club",
    "Language Exchange",
    "Cooking Club",
    "Astronomy Club",
    "Fashion Club",
    "Entrepreneurship Club",
    "Poetry Society",
    "Martial Arts Club",
    "Cycling Club",
    "AI Innovators Club",
    "Business Leaders Network",
    "Music Producers Hub",
    "Finance Society",
    "Student Journal",
    "Tech Entrepreneurs",
    "Digital Art Crew",
    "Startup Founders Club",
    "Public Speaking Association",
    "Philosophy Circle",
    "Volleyball Club",
    "Basketball Team",
    "Football Society",
    "Mountain Hikers",
    "Chess Masters",
    "Space Explorers",
    "Debate and Diplomacy Society",
    "Green Earth Initiative",
    "Coding for Good",
    "Women in Tech",
    "Health and Wellness Club",
    "AI Research Group",
    "Creative Writing Workshop",
    "Human Rights Society",
    "Esports Association",
    "Drama Improv Troupe",
    "Data Science Club",
    "Photography Lounge",
    "Cultural Exchange Circle",
    "Innovation Hub"
  ]
}